reachy_sdk_api/__init__.py
reachy_sdk_api/any_joint_command_pb2.py
reachy_sdk_api/any_joint_command_pb2_grpc.py
reachy_sdk_api/any_mobile_base_command_pb2.py
reachy_sdk_api/any_mobile_base_command_pb2_grpc.py
reachy_sdk_api/arm_kinematics_pb2.py
reachy_sdk_api/arm_kinematics_pb2_grpc.py
reachy_sdk_api/camera_reachy_pb2.py
reachy_sdk_api/camera_reachy_pb2_grpc.py
reachy_sdk_api/config_pb2.py
reachy_sdk_api/config_pb2_grpc.py
reachy_sdk_api/exo_arm_pb2.py
reachy_sdk_api/exo_arm_pb2_grpc.py
reachy_sdk_api/fan_pb2.py
reachy_sdk_api/fan_pb2_grpc.py
reachy_sdk_api/fullbody_cartesian_command_pb2.py
reachy_sdk_api/fullbody_cartesian_command_pb2_grpc.py
reachy_sdk_api/head_kinematics_pb2.py
reachy_sdk_api/head_kinematics_pb2_grpc.py
reachy_sdk_api/joint_pb2.py
reachy_sdk_api/joint_pb2_grpc.py
reachy_sdk_api/kinematics_pb2.py
reachy_sdk_api/kinematics_pb2_grpc.py
reachy_sdk_api/mobile_platform_reachy_pb2.py
reachy_sdk_api/mobile_platform_reachy_pb2_grpc.py
reachy_sdk_api/orbita_kinematics_pb2.py
reachy_sdk_api/orbita_kinematics_pb2_grpc.py
reachy_sdk_api/realsense_pb2.py
reachy_sdk_api/realsense_pb2_grpc.py
reachy_sdk_api/restart_signal_pb2.py
reachy_sdk_api/restart_signal_pb2_grpc.py
reachy_sdk_api/sensor_pb2.py
reachy_sdk_api/sensor_pb2_grpc.py
reachy_sdk_api/trajectory_pb2.py
reachy_sdk_api/trajectory_pb2_grpc.py
reachy_sdk_api-0.7.3.dist-info/METADATA
reachy_sdk_api-0.7.3.dist-info/WHEEL
reachy_sdk_api-0.7.3.dist-info/top_level.txt
reachy_sdk_api-0.7.3.dist-info/RECORD
