Metadata-Version: 2.1
Name: reachy-sdk-api
Version: 0.7.3
Summary: gRPC Protobuf API definition for Reachy SDK.
Home-page: https://github.com/pollen-robotics/reachy-sdk-api
Author: Pollen Robotics
Author-email: contact@pollen-robotics.com
